{
	"title": "The Deathworlders",
	"creator": "Hambone3110",
	"patreon": "https://www.patreon.com/HamboneHFY",
	"filters": {
		"reddit": [
			"from-reddit-post",
			"clean-reddit",
			"custom-break-to-hr",
			"no-preamble",
			"jverse-the-deathworlders",
			"typography",
			"finalize"
		],
		"hfy-archive": [
			"from-hfy-archive",
			"clean-reddit",
			"custom-break-to-hr",
			"no-preamble",
			"jverse-the-deathworlders",
			"typography",
			"finalize"
		]
	},
	"filename": "The Deathworlders",
	"output": ["epub", "latex", "html"],
	"contents":
	[
		{
			"title": "Chapter 0: The Kevin Jenkins Experience",
			"filters": "hfy-archive",
			"src": "http://hfy-archive.org/book/deathworlders/chapter-01-kevin-jenkins-experience"
		}
	]
}
